build_monitor_cli/__init__.py
build_monitor_cli/build.py
build_monitor_cli/cli.py
build_monitor_cli/config.py
build_monitor_cli/main.py
build_monitor_cli-1.0.2.dist-info/METADATA
build_monitor_cli-1.0.2.dist-info/WHEEL
build_monitor_cli-1.0.2.dist-info/entry_points.txt
build_monitor_cli-1.0.2.dist-info/top_level.txt
build_monitor_cli-1.0.2.dist-info/RECORD
